catpdf/__init__.py
catpdf/__main__.py
catpdf-0.9.9.dist-info/entry_points.txt
catpdf-0.9.9.dist-info/WHEEL
catpdf-0.9.9.dist-info/METADATA
catpdf-0.9.9.dist-info/RECORD
